media_fixer/__init__.py
media_fixer/__main__.py
media_fixer/cli.py
media_fixer/core.py
media_fixer-1.0.0.dist-info/METADATA
media_fixer-1.0.0.dist-info/WHEEL
media_fixer-1.0.0.dist-info/top_level.txt
media_fixer-1.0.0.dist-info/RECORD
