Metadata-Version: 2.1
Name: media-fixer
Version: 1.0.0
Summary: A wrapper around ffmpeg to make it work in a concurrent and memory-buffered fashion.
Home-page: https://github.com/simsekhalit/media-fixer
Author: Halit Şimşek
Author-email: mail.simsekhalit@gmail.com
License: MIT
Keywords: audio,buffer,concurrent,conversion,decode,dts,eac3,encode,ffmpeg,fix,media,multimedia
Platform: UNKNOWN
Classifier: Development Status :: 5 - Production/Stable
Classifier: License :: OSI Approved :: MIT License
Classifier: Programming Language :: Python
Classifier: Programming Language :: Python :: 3
Classifier: Programming Language :: Python :: 3.8
Classifier: Programming Language :: Python :: 3.9
Classifier: Programming Language :: Python :: 3.10
Classifier: Programming Language :: Python :: 3.11
Classifier: Programming Language :: Python :: Implementation :: CPython
Classifier: Programming Language :: Python :: Implementation :: PyPy
Classifier: Topic :: Multimedia :: Sound/Audio :: Conversion
Requires-Python: >=3.8
Requires-Dist: psutil
